MANIFEST.in
VERSION
requirements.txt
setup.py
docs/source/conf.py
ibrb.ext.meta.egg-info/PKG-INFO
ibrb.ext.meta.egg-info/SOURCES.txt
ibrb.ext.meta.egg-info/dependency_links.txt
ibrb.ext.meta.egg-info/requires.txt
ibrb.ext.meta.egg-info/top_level.txt
ibrb/ext/meta/__init__.py
ibrb/ext/meta/package.json
ibrb/ext/meta/orm/__init__.py
ibrb/ext/meta/orm/base.py
ibrb/ext/meta/orm/networkaddresses.py
ibrb/ext/meta/orm/networks.py
ibrb/ext/meta/orm/networktokens.py
ibrb/ext/meta/orm/networktransactions.py
ibrb/ext/meta/orm/networktransfers.py
ibrb/ext/meta/orm/smartcontracts.py
ibrb/ext/meta/tests/__init__.py
ibrb/ext/meta/tests/test_integration_noop.py
ibrb/ext/meta/tests/test_system_noop.py
ibrb/ext/meta/tests/test_unit_noop.py